{
    "uuid": [
        {
            "value": "4dd02041-3c38-4152-aa0b-5220b2e5f4f9"
        }
    ],
    "langcode": [
        {
            "value": "en"
        }
    ],
    "type": [
        {
            "target_id": "article",
            "target_type": "node_type",
            "target_uuid": "5fecaee3-df48-4276-97e7-eb9de61f8096"
        }
    ],
    "revision_timestamp": [
        {
            "value": "2019-07-08T05:40:13+00:00",
            "format": "Y-m-d\\TH:i:sP"
        }
    ],
    "revision_uid": [
        {
            "target_type": "user",
            "target_uuid": "4acb7144-e010-4f54-a5f5-978a4fa873a1"
        }
    ],
    "revision_log": [],
    "status": [
        {
            "value": true
        }
    ],
    "uid": [
        {
            "target_type": "user",
            "target_uuid": "4acb7144-e010-4f54-a5f5-978a4fa873a1"
        }
    ],
    "title": [
        {
            "value": "#1"
        }
    ],
    "created": [
        {
            "value": "2019-07-08T05:39:57+00:00",
            "format": "Y-m-d\\TH:i:sP"
        }
    ],
    "changed": [
        {
            "value": "2019-07-08T05:40:13+00:00",
            "format": "Y-m-d\\TH:i:sP"
        }
    ],
    "promote": [
        {
            "value": true
        }
    ],
    "sticky": [
        {
            "value": false
        }
    ],
    "default_langcode": [
        {
            "value": true
        }
    ],
    "revision_translation_affected": [
        {
            "value": true
        }
    ],
    "path": [
        {
            "alias": "",
            "pid": null,
            "langcode": "en"
        }
    ],
    "body": [
        {
            "value": "<p>1111111111111<\/p>\r\n\r\n<p>11111111111111<\/p>\r\n\r\n<p>&nbsp;<\/p>\r\n",
            "format": "basic_html",
            "summary": ""
        }
    ],
    "comment": [
        {
            "status": 2,
            "cid": 0,
            "last_comment_timestamp": 0,
            "last_comment_name": "",
            "last_comment_uid": 0,
            "comment_count": 0
        }
    ],
    "field_image": [],
    "field_tags": []
}